Workbook

Sheet Raw Data
A1: Company | B1: Year | C1: Sales (Rs Cr) | D1: Net Profit (Rs Cr) | E1: PBT (Rs Cr) | F1: Interest (Rs Cr) | G1: Equity Capital (Rs Cr) | H1: Reserves (Rs Cr) | I1: Borrowings (Rs Cr) | J1: Other Liabilities (Rs Cr) | K1: Total Assets (Rs Cr) | L1: Receivables (Rs Cr) | M1: Inventory (Rs Cr) | N1: Cash & Bank (Rs Cr)
A2: TCS | B2: FY2021-22 | C2: 191754 | D2: 38327 | E2: 51687 | F2: 784 | G2: 366 | H2: 88773 | I2: 7818 | J2: 43967 | K2: 140924 | L2: 41810 | M2: 20 | N2: 18221
A3: TCS | B3: FY2022-23 | C3: 225458 | D3: 42147 | E3: 56907 | F3: 779 | G3: 366 | H3: 90058 | I3: 7688 | J3: 44747 | K3: 142859 | L3: 49954 | M3: 28 | N3: 11032
A4: TCS | B4: FY2023-24 | C4: 240893 | D4: 45908 | E4: 61997 | F4: 778 | G4: 362 | H4: 90127 | I4: 8021 | J4: 46962 | K4: 145472 | L4: 53577 | M4: 28 | N4: 13286
A5: TCS | B5: FY2024-25 | C5: 255324 | D5: 48553 | E5: 65331 | F5: 796 | G5: 362 | H5: 94394 | I5: 9392 | J5: 54501 | K5: 158649 | L5: 59046 | M5: 21 | N5: 15463
A6: TCS | B6: FY2025-26 | C6: 267021 | D6: 49210 | E6: 65487 | F6: 1227 | G6: 362 | H6: 106878 | I6: 11283 | J6: 62644 | K6: 181167 | L6: 67714 | M6: 29 | N6: 12908
A7: Infosys | B7: FY2021-22 | C7: 121641 | D7: 22110 | E7: 30110 | F7: 200 | G7: 2098 | H7: 73252 | I7: 5474 | J7: 35905 | K7: 116729 | L7: 22698 | M7: 0 | N7: 17472
A8: Infosys | B8: FY2022-23 | C8: 146767 | D8: 24095 | E8: 33322 | F8: 284 | G8: 2069 | H8: 73338 | I8: 8299 | J8: 40890 | K8: 124596 | L8: 25424 | M8: 0 | N8: 12173
A9: Infosys | B9: FY2023-24 | C9: 153670 | D9: 26233 | E9: 35988 | F9: 470 | G9: 2071 | H9: 86045 | I9: 8359 | J9: 39545 | K9: 136020 | L9: 30193 | M9: 0 | N9: 14786
A10: Infosys | B10: FY2024-25 | C10: 162990 | D10: 26713 | E10: 37608 | F10: 416 | G10: 2073 | H10: 93745 | I10: 8227 | J10: 43750 | K10: 147795 | L10: 31158 | M10: 0 | N10: 24455
A11: Infosys | B11: FY2025-26 | C11: 178650 | D11: 29440 | E11: 39995 | F11: 416 | G11: 2024 | H11: 90828 | I11: 9176 | J11: 52260 | K11: 154288 | L11: 35234 | M11: 0 | N11: 22201
A12: Wipro | B12: FY2021-22 | C12: 79312 | D12: 12229.6 | E12: 15140.8 | F12: 532.5 | G12: 1096.4 | H12: 64306.6 | I12: 17592.9 | J12: 24279.7 | K12: 107275.6 | L12: 11521.9 | M12: 133.4 | N12: 10383.6
A13: Wipro | B13: FY2022-23 | C13: 90487.6 | D13: 11350 | E13: 14765.7 | F13: 1007.7 | G13: 1097.6 | H13: 76570.3 | I13: 17466.6 | J13: 21789.2 | K13: 116923.7 | L13: 12635 | M13: 118.8 | N13: 9188
... A26: Tech Mahindra | B26: FY2025-26 | C26: 56815.4 | D26: 4810.9 | E26: 6573.1 | F26: 337.4 | G26: 442.8 | H26: 29172.6 | I26: 2186.2 | J26: 17366.1 | K26: 49167.7 | L26: 13357.7 | M26: 104.2 | N26: 5105.4

Sheet Source Note
A1: Data Source
A3: Source: screener.in (Consolidated financials), FY2021-22 to FY2025-26
A4: All figures in Rs. Crores unless stated
A6: Note on Current Ratio: Screener.in does not separate current vs non-current liabilities.
A7: Current Ratio below is an approximation using (Receivables+Inventory+Cash & Bank) / Other Liabilities.
A8: This should be flagged as a limitation in the Methodology/Limitations section of the paper.

Sheet Ratios
A1: Company | B1: Year | C1: Net Profit Margin (%) | D1: ROE (%) | E1: ROCE (%) | F1: Debt-Equity Ratio | G1: Current Ratio (approx) | H1: Asset Turnover Ratio
A2: ='Raw Data'!A2 -> TCS | B2: ='Raw Data'!B2 -> FY2021-22 | C2: ='Raw Data'!D2/'Raw Data'!C2*100 -> 19.987588 | D2: ='Raw Data'!D2/('Raw Data'!G2+'Raw Data'!H2)*100 -> 42.996892 | E2: =('Raw Data'!E2+'Raw Data'!F2)/('Raw Data'!G2+'Raw Data'!H2+'Raw Data'!I2)*100 -> 54.117805 | F2: ='Raw Data'!I2/('Raw Data'!G2+'Raw Data'!H2) -> 0.087705718 | G2: =('Raw Data'!L2+'Raw Data'!M2+'Raw Data'!N2)/'Raw Data'!J2 -> 1.3658198 | H2: ='Raw Data'!C2/'Raw Data'!K2 -> 1.3606909
A3: ='Raw Data'!A3 -> TCS | B3: ='Raw Data'!B3 -> FY2022-23 | C3: ='Raw Data'!D3/'Raw Data'!C3*100 -> 18.693947 | D3: ='Raw Data'!D3/('Raw Data'!G3+'Raw Data'!H3)*100 -> 46.610413 | E3: =('Raw Data'!E3+'Raw Data'!F3)/('Raw Data'!G3+'Raw Data'!H3+'Raw Data'!I3)*100 -> 58.79607 | F3: ='Raw Data'!I3/('Raw Data'!G3+'Raw Data'!H3) -> 0.085021676 | G3: =('Raw Data'!L3+'Raw Data'!M3+'Raw Data'!N3)/'Raw Data'!J3 -> 1.3635328 | H3: ='Raw Data'!C3/'Raw Data'!K3 -> 1.5781855
A4: ='Raw Data'!A4 -> TCS | B4: ='Raw Data'!B4 -> FY2023-24 | C4: ='Raw Data'!D4/'Raw Data'!C4*100 -> 19.057424 | D4: ='Raw Data'!D4/('Raw Data'!G4+'Raw Data'!H4)*100 -> 50.733238 | E4: =('Raw Data'!E4+'Raw Data'!F4)/('Raw Data'!G4+'Raw Data'!H4+'Raw Data'!I4)*100 -> 63.724495 | F4: ='Raw Data'!I4/('Raw Data'!G4+'Raw Data'!H4) -> 0.088640608 | G4: =('Raw Data'!L4+'Raw Data'!M4+'Raw Data'!N4)/'Raw Data'!J4 -> 1.4243644 | H4: ='Raw Data'!C4/'Raw Data'!K4 -> 1.6559407
A5: ='Raw Data'!A5 -> TCS | B5: ='Raw Data'!B5 -> FY2024-25 | C5: ='Raw Data'!D5/'Raw Data'!C5*100 -> 19.01623 | D5: ='Raw Data'!D5/('Raw Data'!G5+'Raw Data'!H5)*100 -> 51.240027 | E5: =('Raw Data'!E5+'Raw Data'!F5)/('Raw Data'!G5+'Raw Data'!H5+'Raw Data'!I5)*100 -> 63.493298 | F5: ='Raw Data'!I5/('Raw Data'!G5+'Raw Data'!H5) -> 0.099117734 | G5: =('Raw Data'!L5+'Raw Data'!M5+'Raw Data'!N5)/'Raw Data'!J5 -> 1.3674978 | H5: ='Raw Data'!C5/'Raw Data'!K5 -> 1.6093641
A6: ='Raw Data'!A6 -> TCS | B6: ='Raw Data'!B6 -> FY2025-26 | C6: ='Raw Data'!D6/'Raw Data'!C6*100 -> 18.429262 | D6: ='Raw Data'!D6/('Raw Data'!G6+'Raw Data'!H6)*100 -> 45.887728 | E6: =('Raw Data'!E6+'Raw Data'!F6)/('Raw Data'!G6+'Raw Data'!H6+'Raw Data'!I6)*100 -> 56.287809 | F6: ='Raw Data'!I6/('Raw Data'!G6+'Raw Data'!H6) -> 0.10521261 | G6: =('Raw Data'!L6+'Raw Data'!M6+'Raw Data'!N6)/'Raw Data'!J6 -> 1.2874497 | H6: ='Raw Data'!C6/'Raw Data'!K6 -> 1.4738943
A7: ='Raw Data'!A7 -> Infosys | B7: ='Raw Data'!B7 -> FY2021-22 | C7: ='Raw Data'!D7/'Raw Data'!C7*100 -> 18.176437 | D7: ='Raw Data'!D7/('Raw Data'!G7+'Raw Data'!H7)*100 -> 29.343066 | E7: =('Raw Data'!E7+'Raw Data'!F7)/('Raw Data'!G7+'Raw Data'!H7+'Raw Data'!I7)*100 -> 37.501237 | F7: ='Raw Data'!I7/('Raw Data'!G7+'Raw Data'!H7) -> 0.072647644 | G7: =('Raw Data'!L7+'Raw Data'!M7+'Raw Data'!N7)/'Raw Data'!J7 -> 1.1187857 | H7: ='Raw Data'!C7/'Raw Data'!K7 -> 1.0420804
A8: ='Raw Data'!A8 -> Infosys | B8: ='Raw Data'!B8 -> FY2022-23 | C8: ='Raw Data'!D8/'Raw Data'!C8*100 -> 16.417178 | D8: ='Raw Data'!D8/('Raw Data'!G8+'Raw Data'!H8)*100 -> 31.953267 | E8: =('Raw Data'!E8+'Raw Data'!F8)/('Raw Data'!G8+'Raw Data'!H8+'Raw Data'!I8)*100 -> 40.14766 | F8: ='Raw Data'!I8/('Raw Data'!G8+'Raw Data'!H8) -> 0.1100561 | G8: =('Raw Data'!L8+'Raw Data'!M8+'Raw Data'!N8)/'Raw Data'!J8 -> 0.91946686 | H8: ='Raw Data'!C8/'Raw Data'!K8 -> 1.1779431
A9: ='Raw Data'!A9 -> Infosys | B9: ='Raw Data'!B9 -> FY2023-24 | C9: ='Raw Data'!D9/'Raw Data'!C9*100 -> 17.070996 | D9: ='Raw Data'!D9/('Raw Data'!G9+'Raw Data'!H9)*100 -> 29.770984 | E9: =('Raw Data'!E9+'Raw Data'!F9)/('Raw Data'!G9+'Raw Data'!H9+'Raw Data'!I9)*100 -> 37.790101 | F9: ='Raw Data'!I9/('Raw Data'!G9+'Raw Data'!H9) -> 0.094863589 | G9: =('Raw Data'!L9+'Raw Data'!M9+'Raw Data'!N9)/'Raw Data'!J9 -> 1.1374131 | H9: ='Raw Data'!C9/'Raw Data'!K9 -> 1.1297603
A10: ='Raw Data'!A10 -> Infosys | B10: ='Raw Data'!B10 -> FY2024-25 | C10: ='Raw Data'!D10/'Raw Data'!C10*100 -> 16.389349 | D10: ='Raw Data'!D10/('Raw Data'!G10+'Raw Data'!H10)*100 -> 27.878895 | E10: =('Raw Data'!E10+'Raw Data'!F10)/('Raw Data'!G10+'Raw Data'!H10+'Raw Data'!I10)*100 -> 36.545725 | F10: ='Raw Data'!I10/('Raw Data'!G10+'Raw Data'!H10) -> 0.085860694 | G10: =('Raw Data'!L10+'Raw Data'!M10+'Raw Data'!N10)/'Raw Data'!J10 -> 1.2711543 | H10: ='Raw Data'!C10/'Raw Data'!K10 -> 1.1028113
A11: ='Raw Data'!A11 -> Infosys | B11: ='Raw Data'!B11 -> FY2025-26 | C11: ='Raw Data'!D11/'Raw Data'!C11*100 -> 16.479149 | D11: ='Raw Data'!D11/('Raw Data'!G11+'Raw Data'!H11)*100 -> 31.706371 | E11: =('Raw Data'!E11+'Raw Data'!F11)/('Raw Data'!G11+'Raw Data'!H11+'Raw Data'!I11)*100 -> 39.607755 | F11: ='Raw Data'!I11/('Raw Data'!G11+'Raw Data'!H11) -> 0.098823935 | G11: =('Raw Data'!L11+'Raw Data'!M11+'Raw Data'!N11)/'Raw Data'!J11 -> 1.0990241 | H11: ='Raw Data'!C11/'Raw Data'!K11 -> 1.1578995
A12: ='Raw Data'!A12 -> Wipro | B12: ='Raw Data'!B12 -> FY2021-22 | C12: ='Raw Data'!D12/'Raw Data'!C12*100 -> 15.419609 | D12: ='Raw Data'!D12/('Raw Data'!G12+'Raw Data'!H12)*100 -> 18.698836 | E12: =('Raw Data'!E12+'Raw Data'!F12)/('Raw Data'!G12+'Raw Data'!H12+'Raw Data'!I12)*100 -> 18.884427 | F12: ='Raw Data'!I12/('Raw Data'!G12+'Raw Data'!H12) -> 0.26899225 | G12: =('Raw Data'!L12+'Raw Data'!M12+'Raw Data'!N12)/'Raw Data'!J12 -> 0.90770891 | H12: ='Raw Data'!C12/'Raw Data'!K12 -> 0.73932935
A13: ='Raw Data'!A13 -> Wipro | B13: ='Raw Data'!B13 -> FY2022-23 | C13: ='Raw Data'!D13/'Raw Data'!C13*100 -> 12.543155 | D13: ='Raw Data'!D13/('Raw Data'!G13+'Raw Data'!H13)*100 -> 14.613502 | E13: =('Raw Data'!E13+'Raw Data'!F13)/('Raw Data'!G13+'Raw Data'!H13+'Raw Data'!I13)*100 -> 16.580105 | F13: ='Raw Data'!I13/('Raw Data'!G13+'Raw Data'!H13) -> 0.22488827 | G13: =('Raw Data'!L13+'Raw Data'!M13+'Raw Data'!N13)/'Raw Data'!J13 -> 1.0070035 | H13: ='Raw Data'!C13/'Raw Data'!K13 -> 0.77390298
... A26: ='Raw Data'!A26 -> Tech Mahindra | B26: ='Raw Data'!B26 -> FY2025-26 | C26: ='Raw Data'!D26/'Raw Data'!C26*100 -> 8.4675986 | D26: ='Raw Data'!D26/('Raw Data'!G26+'Raw Data'!H26)*100 -> 16.244589 | E26: =('Raw Data'!E26+'Raw Data'!F26)/('Raw Data'!G26+'Raw Data'!H26+'Raw Data'!I26)*100 -> 21.730039 | F26: ='Raw Data'!I26/('Raw Data'!G26+'Raw Data'!H26) -> 0.073819702 | G26: =('Raw Data'!L26+'Raw Data'!M26+'Raw Data'!N26)/'Raw Data'!J26 -> 1.0691692 | H26: ='Raw Data'!C26/'Raw Data'!K26 -> 1.1555432

Sheet Charts
A1: Net Profit Trend (Rs Cr)
A2: Year | B2: TCS | C2: Infosys | D2: Wipro | E2: HCL Technologies | F2: Tech Mahindra
A3: FY2021-22 | B3: ='Raw Data'!D2 -> 38327 | C3: ='Raw Data'!D7 -> 22110 | D3: ='Raw Data'!D12 -> 12229.6 | E3: ='Raw Data'!D17 -> 13499 | F3: ='Raw Data'!D22 -> 5566.1
A4: FY2022-23 | B4: ='Raw Data'!D3 -> 42147 | C4: ='Raw Data'!D8 -> 24095 | D4: ='Raw Data'!D13 -> 11350 | E4: ='Raw Data'!D18 -> 14851 | F4: ='Raw Data'!D23 -> 4831.3
A5: FY2023-24 | B5: ='Raw Data'!D4 -> 45908 | C5: ='Raw Data'!D9 -> 26233 | D5: ='Raw Data'!D14 -> 11045.2 | E5: ='Raw Data'!D19 -> 15702 | F5: ='Raw Data'!D24 -> 2357.8
A6: FY2024-25 | B6: ='Raw Data'!D5 -> 48553 | C6: ='Raw Data'!D10 -> 26713 | D6: ='Raw Data'!D15 -> 13135.4 | E6: ='Raw Data'!D20 -> 17390 | F6: ='Raw Data'!D25 -> 4251.5
A7: FY2025-26 | B7: ='Raw Data'!D6 -> 49210 | C7: ='Raw Data'!D11 -> 29440 | D7: ='Raw Data'!D16 -> 13197.4 | E7: ='Raw Data'!D21 -> 16642 | F7: ='Raw Data'!D26 -> 4810.9
A9: ROE Comparison (%)
A10: Year | B10: TCS | C10: Infosys | D10: Wipro | E10: HCL Technologies | F10: Tech Mahindra
A11: FY2021-22 | B11: =Ratios!D2 -> 42.996892 | C11: =Ratios!D7 -> 29.343066 | D11: =Ratios!D12 -> 18.698836 | E11: =Ratios!D17 -> 21.802823 | F11: =Ratios!D22 -> 20.702827
A12: FY2022-23 | B12: =Ratios!D3 -> 46.610413 | C12: =Ratios!D8 -> 31.953267 | D12: =Ratios!D13 -> 14.613502 | E12: =Ratios!D18 -> 22.706215 | F12: =Ratios!D23 -> 17.301295
A13: FY2023-24 | B13: =Ratios!D4 -> 50.733238 | C13: =Ratios!D9 -> 29.770984 | D13: =Ratios!D14 -> 14.819208 | E13: =Ratios!D19 -> 23.002212 | F13: =Ratios!D24 -> 8.8408438
A14: FY2024-25 | B14: =Ratios!D5 -> 51.240027 | C14: =Ratios!D10 -> 27.878895 | D14: =Ratios!D15 -> 15.947968 | E14: =Ratios!D20 -> 24.965903 | F14: =Ratios!D25 -> 15.538256
A15: FY2025-26 | B15: =Ratios!D6 -> 45.887728 | C15: =Ratios!D11 -> 31.706371 | D15: =Ratios!D16 -> 14.993927 | E15: =Ratios!D21 -> 22.140624 | F15: =Ratios!D26 -> 16.244589
